setup.py
stompservice/__init__.py
stompservice/client.py
stompservice/test.py
stompservice.egg-info/PKG-INFO
stompservice.egg-info/SOURCES.txt
stompservice.egg-info/dependency_links.txt
stompservice.egg-info/requires.txt
stompservice.egg-info/top_level.txt
stompservice.egg-info/zip-safe